extract_links/__init__.py
extract_links/cli.py
hyperlink_extractor_jda-1.3.0.dist-info/licenses/LICENSE.txt
hyperlink_extractor_jda-1.3.0.dist-info/METADATA
hyperlink_extractor_jda-1.3.0.dist-info/WHEEL
hyperlink_extractor_jda-1.3.0.dist-info/entry_points.txt
hyperlink_extractor_jda-1.3.0.dist-info/top_level.txt
hyperlink_extractor_jda-1.3.0.dist-info/RECORD
