Metadata-Version: 2.4
Name: hyperlink-extractor-jda
Version: 1.3.0
Summary: Extract hyperlinks and their labels from .docx, .odt, .html, and .pdf documents.
Author-email: Josh Allen <data@bigj.ai>
License-Expression: MIT
Project-URL: Homepage, https://github.com/pqexpert/extract-links
Project-URL: Repository, https://github.com/pqexpert/extract-links
Project-URL: Bug Tracker, https://github.com/pqexpert/extract-links/issues
Classifier: Programming Language :: Python :: 3
Classifier: Operating System :: OS Independent
Requires-Python: >=3.7
License-File: LICENSE.txt
Requires-Dist: beautifulsoup4
Requires-Dist: python-docx
Requires-Dist: odfpy
Requires-Dist: openpyxl
Requires-Dist: PyMuPDF
Requires-Dist: lxml
Dynamic: license-file
